bluebox_auth_client/__init__.py
bluebox_auth_client/api_keys/__init__.py
bluebox_auth_client/api_keys/data_mappers.py
bluebox_auth_client/api_keys/entities.py
bluebox_auth_client/api_keys/errors.py
bluebox_auth_client/api_keys/proto/__init__.py
bluebox_auth_client/api_keys/proto/api_keys_objects_pb2.py
bluebox_auth_client/api_keys/proto/api_keys_objects_pb2_grpc.py
bluebox_auth_client/api_keys/proto/api_keys_services_pb2.py
bluebox_auth_client/api_keys/proto/api_keys_services_pb2_grpc.py
bluebox_auth_client/api_keys/services.py
bluebox_auth_client/errors.py
bluebox_auth_client-0.1.0.dev1.dist-info/METADATA
bluebox_auth_client-0.1.0.dev1.dist-info/WHEEL
bluebox_auth_client-0.1.0.dev1.dist-info/RECORD
